src/__init__.py
src/app.py
src/pyi_patch.py
src/wsl_operations.py
src/systray/__init__.py
src/systray/traybar.py
src/systray/win32_adapter.py
wsl_tray-0.2.dist-info/LICENSE
wsl_tray-0.2.dist-info/METADATA
wsl_tray-0.2.dist-info/WHEEL
wsl_tray-0.2.dist-info/top_level.txt
wsl_tray-0.2.dist-info/RECORD
