Metadata-Version: 2.1
Name: wsl-tray
Version: 0.2
Summary: wsl-tray is a lightweight Windows tray application for easily managing WSL 2 VMs.
Home-page: https://github.com/yzgyyang/wsl-tray
Author: Guangyuan Yang
Author-email: yzgyyang@outlook.com
License: UNKNOWN
Platform: UNKNOWN
Classifier: Programming Language :: Python :: 3 :: Only
Classifier: License :: OSI Approved :: BSD License
Classifier: Operating System :: Microsoft :: Windows :: Windows 10
Requires-Python: >=3.7
